Workbook

Sheet Cover
A2: Title : | B2: Titan Company Ltd. - DCF Valuation Model
A4: Prepared by : | B4: Samya Patel
A6: Objective : | B6: Estimate Titan's Intrinsic value using the Discounted Cash Flow (DCF) method
A8: Methodology: | B8: Discounted Cash Flow (FCFF Approach)
A10: Forecast Period: | B10: FY26–FY30
A12: Terminal Growth Rate: | B12: 0.04
A14: WACC: | B14: 0.0994
A16: Estimated Intrinsic Value: | B16: ₹925.80 per share

Sheet Assumptions
A1: Assumptions Sheet
A3: Assumption | E3: Value
A5: Revenue Growth | E5: 0.18
A7: EBITDA Margin | E7: 0.13
A9: Deprication % | E9: 0.025
A11: CapEx % | E11: 0.032
A13: Tax Rate | E13: 0.25
A15: Working Capital % | E15: 0.15
A17: Terminal Growth Rate | E17: 0.04
A19: WACC | E19: 0.105

Sheet Historical Financials
A1: Historical Financials
A3: Particulars | C3: FY22 | D3: FY23 | E3: FY24 | F3: FY25 | H3: (Crore Rupees)
A5: Revenue | C5: 28799 | D5: 40575 | E5: 51084 | F5: 60456
A7: EBITDA | B7: (approx) | C7: 3450 | D7: 5300 | E7: 6300 | F7: 7200
A9: EBIT | B9: (approx) | C9: 2900 | D9: 4600 | E9: 5600 | F9: 6400
A11: Tax Expense | C11: 784 | D11: 1010 | E11: 1276 | F11: 1340
A13: Depriciation | C13: 500 | D13: 650 | E13: 700 | F13: 780
A15: CapEx | C15: -1120 | D15: -1450 | E15: -1780 | F15: -2050
A17: Working Capital | C17: =C5*Assumptions!E15 -> 4319.85 | D17: =D5*Assumptions!E15 -> 6086.25 | E17: =E5*Assumptions!E15 -> 7662.6 | F17: =F5*Assumptions!E15 -> 9068.4

Sheet Forecasts
A1: Forecasts
A3: Year | B3: FY26 | C3: FY27 | D3: FY28 | E3: FY29 | F3: FY30
A5: Revenue (₹ Cr) | B5: ='Historical Financials'!F5*(1+'Control Panel'!B14) -> 71338.08 | C5: =Forecasts!B5*(1+Assumptions!E5) -> 84178.934 | D5: =Forecasts!C5*(1+Assumptions!E5) -> 99331.143 | E5: =Forecasts!D5*(1+Assumptions!E5) -> 117210.75 | F5: =Forecasts!E5*(1+Assumptions!E5) -> 138308.68
A7: Revenue Growth % | B7: ='Control Panel'!B14 -> 0.18 | C7: ='Control Panel'!B14 -> 0.18 | D7: ='Control Panel'!B14 -> 0.18 | E7: ='Control Panel'!B14 -> 0.18 | F7: ='Control Panel'!B14 -> 0.18
A9: EBITDA Margin % | B9: =Assumptions!E7 -> 0.13 | C9: =Assumptions!E7 -> 0.13 | D9: =Assumptions!E7 -> 0.13 | E9: =Assumptions!E7 -> 0.13 | F9: =Assumptions!E7 -> 0.13
A11: EBITDA (₹ Cr) | B11: =B5*'Control Panel'!B16 -> 9273.9504 | C11: =C5*'Control Panel'!B16 -> 10943.261 | D11: =D5*'Control Panel'!B16 -> 12913.049 | E11: =E5*'Control Panel'!B16 -> 15237.397 | F11: =F5*'Control Panel'!B16 -> 17980.129
A13: Depriciation % Revenue | B13: =Assumptions!E9 -> 0.025 | C13: =Assumptions!E9 -> 0.025 | D13: =Assumptions!E9 -> 0.025 | E13: =Assumptions!E9 -> 0.025 | F13: =Assumptions!E9 -> 0.025
A15: Depriciation (₹ Cr) | B15: =B5*'Control Panel'!B18 -> 2140.1424 | C15: =C5*'Control Panel'!B18 -> 2525.368 | D15: =D5*'Control Panel'!B18 -> 2979.9343 | E15: =E5*'Control Panel'!B18 -> 3516.3224 | F15: =F5*'Control Panel'!B18 -> 4149.2605
A17: EBIT | B17: =B11-B15 -> 7133.808 | C17: =C11-C15 -> 8417.8934 | D17: =D11-D15 -> 9933.1143 | E17: =E11-E15 -> 11721.075 | F17: =F11-F15 -> 13830.868
A19: Tax Rate | B19: ='Control Panel'!B24 -> 0.25 | C19: ='Control Panel'!B24 -> 0.25 | D19: ='Control Panel'!B24 -> 0.25 | E19: ='Control Panel'!B24 -> 0.25 | F19: ='Control Panel'!B24 -> 0.25
A21: Tax Expense | B21: =B17*(1-B19) -> 5350.356 | C21: =C17*(1-C19) -> 6313.4201 | D21: =D17*(1-D19) -> 7449.8357 | E21: =E17*(1-E19) -> 8790.8061 | F21: =F17*(1-F19) -> 10373.151
A23: NOPAT | B23: =B17-B21 -> 1783.452 | C23: =C17-C21 -> 2104.4734 | D23: =D17-D21 -> 2483.2786 | E23: =E17-E21 -> 2930.2687 | F23: =F17-F21 -> 3457.7171
A25: CapEx % Revenue | B25: =Assumptions!E11 -> 0.032 | C25: =Assumptions!E11 -> 0.032 | D25: =Assumptions!E11 -> 0.032 | E25: =Assumptions!E11 -> 0.032 | F25: =Assumptions!E11 -> 0.032
A27: CapEx | B27: =B5*'Control Panel'!B20 -> 2140.1424 | C27: =C5*'Control Panel'!B20 -> 2525.368 | D27: =D5*'Control Panel'!B20 -> 2979.9343 | E27: =E5*'Control Panel'!B20 -> 3516.3224 | F27: =F5*'Control Panel'!B20 -> 4149.2605
A29: Working Capital % Revenue | B29: =Assumptions!E15 -> 0.15 | C29: =Assumptions!E15 -> 0.15 | D29: =Assumptions!E15 -> 0.15 | E29: =Assumptions!E15 -> 0.15 | F29: =Assumptions!E15 -> 0.15
A31: Net Working Capital | B31: =B5*'Control Panel'!B22 -> 10700.712 | C31: =C5*'Control Panel'!B22 -> 12626.84 | D31: =D5*'Control Panel'!B22 -> 14899.671 | E31: =E5*'Control Panel'!B22 -> 17581.612 | F31: =F5*'Control Panel'!B22 -> 20746.302
A33: Change in Net Working Capital | B33: =B31-'Historical Financials'!F17 -> 1632.312 | C33: =C31-B31 -> 1926.1282 | D33: =D31-C31 -> 2272.8312 | E33: =E31-D31 -> 2681.9408 | F33: =F31-E31 -> 3164.6902

Sheet FCFF
A1: FCFF
B3: FY26 | C3: FY27 | D3: FY28 | E3: FY29 | F3: FY30
H4: FCFF = | I4: NOPAT + Depriciation - CapEx. - Δ Working Capital
A5: Revenue | B5: =Forecasts!B5 -> 71338.08 | C5: =Forecasts!C5 -> 84178.934 | D5: =Forecasts!D5 -> 99331.143 | E5: =Forecasts!E5 -> 117210.75 | F5: =Forecasts!F5 -> 138308.68
A7: EBIT | B7: =Forecasts!B17 -> 7133.808 | C7: =Forecasts!C17 -> 8417.8934 | D7: =Forecasts!D17 -> 9933.1143 | E7: =Forecasts!E17 -> 11721.075 | F7: =Forecasts!F17 -> 13830.868 | H7: FCFF is the "Cash flow available to all capital providers after reinvestment in operations.”
A9: Tax | B9: =B7*Forecasts!B19 -> 1783.452 | C9: =C7*Forecasts!C19 -> 2104.4734 | D9: =D7*Forecasts!D19 -> 2483.2786 | E9: =E7*Forecasts!E19 -> 2930.2687 | F9: =F7*Forecasts!F19 -> 3457.7171
A11: NOPAT | B11: =B7-B9 -> 5350.356 | C11: =C7-C9 -> 6313.4201 | D11: =D7-D9 -> 7449.8357 | E11: =E7-E9 -> 8790.8061 | F11: =F7-F9 -> 10373.151
A13: (+) D&A | B13: =Forecasts!B15 -> 2140.1424 | C13: =Forecasts!C15 -> 2525.368 | D13: =Forecasts!D15 -> 2979.9343 | E13: =Forecasts!E15 -> 3516.3224 | F13: =Forecasts!F15 -> 4149.2605
A15: (-) Cap Ex. | B15: =Forecasts!B27 -> 2140.1424 | C15: =Forecasts!C27 -> 2525.368 | D15: =Forecasts!D27 -> 2979.9343 | E15: =Forecasts!E27 -> 3516.3224 | F15: =Forecasts!F27 -> 4149.2605
A17: (-) Δ Working Capital | B17: =Forecasts!B33 -> 1632.312 | C17: =Forecasts!C33 -> 1926.1282 | D17: =Forecasts!D33 -> 2272.8312 | E17: =Forecasts!E33 -> 2681.9408 | F17: =Forecasts!F33 -> 3164.6902
A19: FCFF | B19: =B11+B13-B15-B17 -> 3718.044 | C19: =C11+C13-C15-C17 -> 4387.2919 | D19: =D11+D13-D15-D17 -> 5177.0045 | E19: =E11+E13-E15-E17 -> 6108.8653 | F19: =F11+F13-F15-F17 -> 7208.461

Sheet WACC
A1: WACC
A3: Input Section
A5: Item | C5: Value (In Crores ₹)
A7: Risk-Free Rate (Rf) | C7: 0.0635
A9: Beta (β) | C9: 0.83
A11: Market Risk Premium (MRP) | C11: 0.055
A13: Market Value of Equity (E) | C13: 46168
A15: Market Value of Debt (D) | C15: 9646
A17: Tax Rate | C17: 0.25
A19: Calculations | F19: Final Output
A21: Total Value (E + D) | C21: =C13+C15 -> 55814 | F21: WACC = (E/V × Re) + (D/V × Rd × (1-T))
A23: Equity Weight (E/V) | C23: =C13/C21 -> 0.82717598 | F23: =((C23*C27)+(C25*C31)) -> 0.099359519
A25: Debt Weight (D/V) | C25: =C15/C21 -> 0.17282402
F26: Final WACC: 10.8%
A27: Cost of Equity = Rf + β × MRP (Re) | C27: =C7+(C9*C11) -> 0.10915
F28: Interpretation:
A29: Cost of Debt = Interest / Debt | C29: 0.07 | F29: Titan must generate returns above 10.8% to create value for its investors.
F30: This WACC is used to discount projected FCFF and estimate Enterprise Value in the DCF valuation.
A31: After - Tax Cost of Debt = Rd * (1-Tax) | C31: =C29*(1-C17) -> 0.0525

Sheet Valuation
A1: Valuation
I2: Final Output
A3: Input Section | B3: (In Crores)
H4: Step 1: | I4: Sum of PV of FCFF = | K4: Sum of all yearly PVs (5 years)
A5: Item | B5: Source
I6: =SUM(B21:F21) -> 19267.831 | J6: (Crores)
A7: WACC | B7: ='Control Panel'!B26 -> 0.105
H8: Step 2: | I8: Terminal Value (after 5 years) | K8: Value of Company from FY31 till Infinity
A9: Terminal Growth Rate (g) | B9: ='Control Panel'!B28 -> 0.04
I10: TV = FCFF5 (FY30) × (1 + g) / (WACC − g)
A11: Cash & Cash Equivalents | B11: 0
I12: =((1+B9)/(B7-B9))*F19 -> 115335.38 | J12: (Crores)
A13: Total Debt | B13: =WACC!C15 -> 9646
H14: Step 3: | I14: Discount Terminal Value back to Today
A15: Shares Outstanding | B15: 89
I16: PV of TV = TV / (1 + WACC)^5
A17: FCFF Valuation
B18: FY26 | C18: FY27 | D18: FY28 | E18: FY29 | F18: FY30 | I18: =I12/(1+B7)^5 -> 70008.56 | J18: (Crores)
A19: FCFF | B19: =FCFF!B19 -> 3718.044 | C19: =FCFF!C19 -> 4387.2919 | D19: =FCFF!D19 -> 5177.0045 | E19: =FCFF!E19 -> 6108.8653 | F19: =FCFF!F19 -> 7208.461
A20: Discount Factor | B20: =1/(1+B7)^1 -> 0.90497738 | C20: =1/(1+B7)^2 -> 0.81898405 | D20: =1/(1+B7)^3 -> 0.74116204 | E20: =1/(1+B7)^4 -> 0.67073487 | F20: =1/(1+B7)^5 -> 0.60699989 | H20: Step 4: | I20: Enterprise Value (EV) | K20: Enterprise Value is the value of the entire business operations available to both
A21: PV of FCFF | B21: =B19*B20 -> 3364.7457 | C21: =C19*C20 -> 3593.1221 | D21: =D19*D20 -> 3836.9992 | E21: =E19*E20 -> 4097.429 | F21: =F19*F20 -> 4375.535 | K21: debt holders and equity shareholders.
I22: EV = Total PV of FCFF + PV of Terminal | K22: It is not yet the value of shareholders' equity.
A24: Investment Conclusion | I24: =I6+I18 -> 89276.391 | J24: (Crores)
A26: Based on the DCF valuation, Titan Company's estimated intrinsic value is ₹925.80 per share. | H26: Step 5: | I26: Equity Value | J26: Enterprise Value + Cash - Debt
A27: The valuation is derived using a WACC of 9.94% and a terminal growth rate of 4%.
A28: Investors should compare this intrinsic value with the current market price to determine whether the stock | I28: =I24+B11-B13 -> 79630.391 | J28: (Crores)
A29: is undervalued or overvalued .
H30: Step 6: | I30: Intrinsic Value per Share (Rs./Share) | K30: Equity Value (Cr. Rs.) / Share Outstanding (Cr. Shares)
I31: =I28/89 -> 894.7235 | J31: (per share)
A32: The DCF analysis estimates Titan Company's fair value at ₹925.80 per share, | K32: The estimated true or fair value of a company's share based on its future cash-generating ability.
A33: indicating that the stock's attractiveness depends on its prevailing market price relative to this intrinsic value.

Sheet  Sensitivity Analysis
A1: Sensitivity Analysis
A3: Titan Company Ltd. - Sensitivity Analysis
A5: The sensitivity analysis evaluates the impact of changes in WACC and Terminal Growth Rate on the estimated intrinsic value per share.
A7: Base Assumptions
A9: Item | B9: Base Case
A10: WACC | B10: =Valuation!B7 -> 0.105
A11: Terminal Growth Rate (g) | B11: =Valuation!B9 -> 0.04
A12: Intrinsic Value per Share | B12: =Valuation!I31 -> 894.7235
A14: Sensitivity of Intrinsic value per share (₹)
A16: WACC/g | B16: Terminal Growth Rate
A17: =B12 -> 894.7235 | B17: 0.03 | C17: 0.04 | D17: 0.05
A18: 0.0894 | B18: 962.12 | C18: 1145.87 | D18: 1422.9
A19: 0.0994 | B19: 799.63 | C19: 925.73 | D19: 1102.89
A20: 0.1094 | B20: 678.33 | C20: 769.31 | D20: 890.93
A23: Interpretation
A25: Titan's estimated intrinsic value ranges from approximately ₹678 to ₹1,423 per share under different assumptions for WACC and terminal growth.
A26: Under the base-case assumptions of 9.94% WACC and 4% terminal growth, the intrinsic value is estimated at ₹925.73 per share.

Sheet Dashboard 
A1: Titan Company Ltd. - Dashboard
M3: Investment Conclusion
A4: Market Price | D4: Intrinsic Value | G4: Upside/Downside | J4: Recommendation
M6: • Intrinsic Value per Share: ₹925.73
A7: 3850 | D7: =Valuation!I31 -> 894.7235 | G7: =(D7-A7)/A7 -> -0.76760429 | J7: =IF(G7>15%,"BUY",IF(G7<-15%,"SELL","HOLD")) -> SELL | M7: • Current Market Price: ₹3,850.00
M8: • Implied Upside/(Downside): -75.95%
M9: • Recommendation: SELL
A11: Key Metrics Table | E11: Projected FCFF(in Cr.Rs.) | H11: Valuation Comparison Chart
A13: WACC | C13: =Valuation!B7 -> 0.105 | E13: Year | F13: FCFF | H13: Market Price | J13: =A7 -> 3850 | M13: Under the base-case assumptions of 9.94% WACC and 4.00% terminal growth,
A14: Terminal growth | C14: =Valuation!B9 -> 0.04 | E14: FY26 | F14: =Valuation!B19 -> 3718.044 | H14: Intrinsic Value | J14: =D7 -> 894.7235 | M14: Titan's intrinsic value is estimated at ₹925.73 per share,
A15: Enterprise Value (In Cr.) | C15: =Valuation!I24 -> 89276.391 | E15: FY27 | F15: =Valuation!C19 -> 4387.2919 | M15: compared with the current market price of ₹3,850 per share.
A16: Equity Value (In Cr.) | C16: =Valuation!I28 -> 79630.391 | E16: FY28 | F16: =Valuation!D19 -> 5177.0045 | M16: This implies a downside of 75.95%, resulting in a SELL recommendation.
A17: Intrinsic Value | C17: =Valuation!I31 -> 894.7235 | E17: FY29 | F17: =Valuation!E19 -> 6108.8653
E18: FY30 | F18: =Valuation!F19 -> 7208.461

Sheet Control Panel
A1: DCF Control Panel
A3: Company Information
A5: Company Name | B5: Titan Company Ltd.
A6: Current Share Price | B6: 4461.1
A7: Shares Outstanding | B7: =Valuation!B15 -> 89
A8: Net Debt | B8: =Valuation!B13 -> 9646
A10: Forecast Assumptions
A12: Forecast Years | B12: 7 | H12: Forecast Years | I12: Scenarios
H13: 5 | I13: Bear
A14: Revenue Growth | B14: 0.18 | H14: 7 | I14: Base
H15: 10 | I15: Bull
A16: EBITDA Margin | B16: 0.13
A18: Depriciation % Revenue | B18: 0.03
A20: CapEx % Revenue | B20: 0.03
A22: Working Capital % Revenue | B22: 0.15
A24: Tax Rate | B24: 0.25
A26: WACC | B26: 0.105 | F26: Note: Forecast Year and Scenario selectors are reserved for future enhancements and are not currently linked to the model.
A28: Terminal Growth | B28: 0.04
A30: Scenerio | B30: Bear
